inventory/__init__.py
inventory/admin.py
inventory/apps.py
inventory/context_processors.py
inventory/models.py
inventory/tests.py
inventory/urls.py
inventory/views.py
inventory/migrations/__init__.py
django_ecomstore_inventory-0.0.1.dist-info/LICENSE
django_ecomstore_inventory-0.0.1.dist-info/METADATA
django_ecomstore_inventory-0.0.1.dist-info/WHEEL
django_ecomstore_inventory-0.0.1.dist-info/top_level.txt
django_ecomstore_inventory-0.0.1.dist-info/RECORD
